assetreload
