Metadata-Version: 1.0
Name: assetreload
Version: 1.0.1
Summary: Broadcast changes in your assets to the browser.
Home-page: https://github.com/callum-/assetreload
Author: Callum Jefferies
Author-email: callum@callumj.co.uk
License: MIT License
Download-URL: http://github.com/callum-/assetreload/archive/1.0.1.tar.gz
Keywords: websocket css javascript web browser tornado
Platform: UNKNOWN
